DFTtoolbox/abinit.py
DFTtoolbox/elk.py
DFTtoolbox/postproc.py
DFTtoolbox/qe.py
DFTtoolbox/struct.py
DFTtoolbox-1.6.2.dist-info/METADATA
DFTtoolbox-1.6.2.dist-info/WHEEL
DFTtoolbox-1.6.2.dist-info/top_level.txt
DFTtoolbox-1.6.2.dist-info/RECORD
