Metadata-Version: 2.1
Name: DFTtoolbox
Version: 1.6.2
Summary: A toolbox to initialize or postpocess several DFT codes
Home-page: https://github.com/pipidog/DFTtoolbox
Author: pipidog
Author-email: pipidog@gmail.com
License: MIT
Download-URL: https://github.com/pipidog/DFTtoolbox/archive/v1.6.2.tar.gz
Keywords: density-functional-theory,qantum-espresso,elk,abinit
Platform: UNKNOWN
Classifier: Topic :: Scientific/Engineering :: Physics
Requires-Dist: numpy
Requires-Dist: matplotlib
